arcane/mct/__init__.py
arcane/mct/client.py
arcane/mct/const.py
arcane/mct/exception.py
arcane/mct/helpers.py
arcane_mct-2.0.6.dist-info/METADATA
arcane_mct-2.0.6.dist-info/WHEEL
arcane_mct-2.0.6.dist-info/RECORD
