Metadata-Version: 2.4
Name: arcane-mct
Version: 2.0.6
Summary: Package description
Author: Arcane
Author-email: product@wearcane.com
Requires-Python: >=3.9,<3.14
Classifier: Programming Language :: Python :: 3
Classifier: Programming Language :: Python :: 3.9
Classifier: Programming Language :: Python :: 3.10
Classifier: Programming Language :: Python :: 3.11
Classifier: Programming Language :: Python :: 3.12
Classifier: Programming Language :: Python :: 3.13
Requires-Dist: arcane-core (>=1,<2)
Requires-Dist: arcane-credentials (>=0.1,<0.2)
Requires-Dist: arcane-datastore (>=1,<2)
Requires-Dist: arcane-requests (>=1,<2)
Requires-Dist: backoff (>=1.10.0)
Requires-Dist: google-api-python-client (>=2.149.0)
